LICENSE.txt
README.md
setup.py
thzabbix/__init__.py
thzabbix/httptest.py
thzabbix/zabbreq.py
thzabbix.egg-info/PKG-INFO
thzabbix.egg-info/SOURCES.txt
thzabbix.egg-info/dependency_links.txt
thzabbix.egg-info/top_level.txt