Metadata-Version: 2.1
Name: thzabbix
Version: 0.1.2
Summary: Package for work with zabbix api
Home-page: https://github.com/thorvaldhrafn/thzabbix
Author: Volodymyr Borysiuk
Author-email: thorvaldr.hrafn@gmail.com
License: MIT License
Platform: UNKNOWN
Classifier: Programming Language :: Python :: 3
Classifier: License :: OSI Approved :: MIT License
Classifier: Operating System :: OS Independent
License-File: LICENSE.txt
